{
    "alias": "JANOSUS",
    "links": [
        {
            "dst": 2,
            "id": 0,
            "length": 1500.0,
            "slots": 320,
            "src": 0
        },
        {
            "dst": 0,
            "id": 1,
            "length": 1500.0,
            "slots": 320,
            "src": 2
        },
        {
            "dst": 4,
            "id": 2,
            "length": 1500.0,
            "slots": 320,
            "src": 0
        },
        {
            "dst": 0,
            "id": 3,
            "length": 1500.0,
            "slots": 320,
            "src": 4
        },
        {
            "dst": 2,
            "id": 4,
            "length": 817.6605877784029,
            "slots": 320,
            "src": 1
        },
        {
            "dst": 1,
            "id": 5,
            "length": 817.6605877784029,
            "slots": 320,
            "src": 2
        },
        {
            "dst": 3,
            "id": 6,
            "length": 568.5537689973014,
            "slots": 320,
            "src": 1
        },
        {
            "dst": 1,
            "id": 7,
            "length": 568.5537689973014,
            "slots": 320,
            "src": 3
        },
        {
            "dst": 5,
            "id": 8,
            "length": 1500.0,
            "slots": 320,
            "src": 1
        },
        {
            "dst": 1,
            "id": 9,
            "length": 1500.0,
            "slots": 320,
            "src": 5
        },
        {
            "dst": 4,
            "id": 10,
            "length": 1443.923286951793,
            "slots": 320,
            "src": 2
        },
        {
            "dst": 2,
            "id": 11,
            "length": 1443.923286951793,
            "slots": 320,
            "src": 4
        },
        {
            "dst": 4,
            "id": 12,
            "length": 888.2868748003677,
            "slots": 320,
            "src": 3
        },
        {
            "dst": 3,
            "id": 13,
            "length": 888.2868748003677,
            "slots": 320,
            "src": 4
        },
        {
            "dst": 5,
            "id": 14,
            "length": 1407.05151144063,
            "slots": 320,
            "src": 3
        },
        {
            "dst": 3,
            "id": 15,
            "length": 1407.05151144063,
            "slots": 320,
            "src": 5
        },
        {
            "dst": 11,
            "id": 16,
            "length": 919.5498361442023,
            "slots": 320,
            "src": 4
        },
        {
            "dst": 4,
            "id": 17,
            "length": 919.5498361442023,
            "slots": 320,
            "src": 11
        },
        {
            "dst": 6,
            "id": 18,
            "length": 1356.880176796738,
            "slots": 320,
            "src": 5
        },
        {
            "dst": 5,
            "id": 19,
            "length": 1356.880176796738,
            "slots": 320,
            "src": 6
        },
        {
            "dst": 7,
            "id": 20,
            "length": 1500.0,
            "slots": 320,
            "src": 5
        },
        {
            "dst": 5,
            "id": 21,
            "length": 1500.0,
            "slots": 320,
            "src": 7
        },
        {
            "dst": 7,
            "id": 22,
            "length": 525.6614856052462,
            "slots": 320,
            "src": 6
        },
        {
            "dst": 6,
            "id": 23,
            "length": 525.6614856052462,
            "slots": 320,
            "src": 7
        },
        {
            "dst": 8,
            "id": 24,
            "length": 573.791736024592,
            "slots": 320,
            "src": 6
        },
        {
            "dst": 6,
            "id": 25,
            "length": 573.791736024592,
            "slots": 320,
            "src": 8
        },
        {
            "dst": 11,
            "id": 26,
            "length": 1500.0,
            "slots": 320,
            "src": 6
        },
        {
            "dst": 6,
            "id": 27,
            "length": 1500.0,
            "slots": 320,
            "src": 11
        },
        {
            "dst": 16,
            "id": 28,
            "length": 1499.83438340173,
            "slots": 320,
            "src": 6
        },
        {
            "dst": 6,
            "id": 29,
            "length": 1499.83438340173,
            "slots": 320,
            "src": 16
        },
        {
            "dst": 21,
            "id": 30,
            "length": 770.9584232572195,
            "slots": 320,
            "src": 7
        },
        {
            "dst": 7,
            "id": 31,
            "length": 770.9584232572195,
            "slots": 320,
            "src": 21
        },
        {
            "dst": 10,
            "id": 32,
            "length": 543.1408066392901,
            "slots": 320,
            "src": 8
        },
        {
            "dst": 8,
            "id": 33,
            "length": 543.1408066392901,
            "slots": 320,
            "src": 10
        },
        {
            "dst": 15,
            "id": 34,
            "length": 846.3620628698229,
            "slots": 320,
            "src": 8
        },
        {
            "dst": 8,
            "id": 35,
            "length": 846.3620628698229,
            "slots": 320,
            "src": 15
        },
        {
            "dst": 10,
            "id": 36,
            "length": 973.2043247667134,
            "slots": 320,
            "src": 9
        },
        {
            "dst": 9,
            "id": 37,
            "length": 973.2043247667134,
            "slots": 320,
            "src": 10
        },
        {
            "dst": 12,
            "id": 38,
            "length": 839.2186011198173,
            "slots": 320,
            "src": 9
        },
        {
            "dst": 9,
            "id": 39,
            "length": 839.2186011198173,
            "slots": 320,
            "src": 12
        },
        {
            "dst": 11,
            "id": 40,
            "length": 1306.925312351537,
            "slots": 320,
            "src": 10
        },
        {
            "dst": 10,
            "id": 41,
            "length": 1306.925312351537,
            "slots": 320,
            "src": 11
        },
        {
            "dst": 15,
            "id": 42,
            "length": 571.4797711167189,
            "slots": 320,
            "src": 10
        },
        {
            "dst": 10,
            "id": 43,
            "length": 571.4797711167189,
            "slots": 320,
            "src": 15
        },
        {
            "dst": 13,
            "id": 44,
            "length": 439.7124128669452,
            "slots": 320,
            "src": 12
        },
        {
            "dst": 12,
            "id": 45,
            "length": 439.7124128669452,
            "slots": 320,
            "src": 13
        },
        {
            "dst": 14,
            "id": 46,
            "length": 607.3384938594429,
            "slots": 320,
            "src": 12
        },
        {
            "dst": 12,
            "id": 47,
            "length": 607.3384938594429,
            "slots": 320,
            "src": 14
        },
        {
            "dst": 15,
            "id": 48,
            "length": 623.4452373958061,
            "slots": 320,
            "src": 12
        },
        {
            "dst": 12,
            "id": 49,
            "length": 623.4452373958061,
            "slots": 320,
            "src": 15
        },
        {
            "dst": 15,
            "id": 50,
            "length": 550.7361701104992,
            "slots": 320,
            "src": 13
        },
        {
            "dst": 13,
            "id": 51,
            "length": 550.7361701104992,
            "slots": 320,
            "src": 15
        },
        {
            "dst": 16,
            "id": 52,
            "length": 591.2435522717495,
            "slots": 320,
            "src": 13
        },
        {
            "dst": 13,
            "id": 53,
            "length": 591.2435522717495,
            "slots": 320,
            "src": 16
        },
        {
            "dst": 17,
            "id": 54,
            "length": 659.6582332449932,
            "slots": 320,
            "src": 13
        },
        {
            "dst": 13,
            "id": 55,
            "length": 659.6582332449932,
            "slots": 320,
            "src": 17
        },
        {
            "dst": 17,
            "id": 56,
            "length": 223.9302256422749,
            "slots": 320,
            "src": 14
        },
        {
            "dst": 14,
            "id": 57,
            "length": 223.9302256422749,
            "slots": 320,
            "src": 17
        },
        {
            "dst": 20,
            "id": 58,
            "length": 793.3267082270377,
            "slots": 320,
            "src": 16
        },
        {
            "dst": 16,
            "id": 59,
            "length": 793.3267082270377,
            "slots": 320,
            "src": 20
        },
        {
            "dst": 23,
            "id": 60,
            "length": 515.0705342016395,
            "slots": 320,
            "src": 16
        },
        {
            "dst": 16,
            "id": 61,
            "length": 515.0705342016395,
            "slots": 320,
            "src": 23
        },
        {
            "dst": 19,
            "id": 62,
            "length": 995.613671639564,
            "slots": 320,
            "src": 17
        },
        {
            "dst": 17,
            "id": 63,
            "length": 995.613671639564,
            "slots": 320,
            "src": 19
        },
        {
            "dst": 25,
            "id": 64,
            "length": 740.011197632198,
            "slots": 320,
            "src": 17
        },
        {
            "dst": 17,
            "id": 65,
            "length": 740.011197632198,
            "slots": 320,
            "src": 25
        },
        {
            "dst": 19,
            "id": 66,
            "length": 350.2728708484958,
            "slots": 320,
            "src": 18
        },
        {
            "dst": 18,
            "id": 67,
            "length": 350.2728708484958,
            "slots": 320,
            "src": 19
        },
        {
            "dst": 22,
            "id": 68,
            "length": 447.4805086812668,
            "slots": 320,
            "src": 18
        },
        {
            "dst": 18,
            "id": 69,
            "length": 447.4805086812668,
            "slots": 320,
            "src": 22
        },
        {
            "dst": 25,
            "id": 70,
            "length": 514.6263190806314,
            "slots": 320,
            "src": 18
        },
        {
            "dst": 18,
            "id": 71,
            "length": 514.6263190806314,
            "slots": 320,
            "src": 25
        },
        {
            "dst": 22,
            "id": 72,
            "length": 346.1409740121352,
            "slots": 320,
            "src": 19
        },
        {
            "dst": 19,
            "id": 73,
            "length": 346.1409740121352,
            "slots": 320,
            "src": 22
        },
        {
            "dst": 23,
            "id": 74,
            "length": 546.8210165297021,
            "slots": 320,
            "src": 20
        },
        {
            "dst": 20,
            "id": 75,
            "length": 546.8210165297021,
            "slots": 320,
            "src": 23
        },
        {
            "dst": 25,
            "id": 76,
            "length": 796.5881016659589,
            "slots": 320,
            "src": 20
        },
        {
            "dst": 20,
            "id": 77,
            "length": 796.5881016659589,
            "slots": 320,
            "src": 25
        },
        {
            "dst": 23,
            "id": 78,
            "length": 1017.988857051166,
            "slots": 320,
            "src": 21
        },
        {
            "dst": 21,
            "id": 79,
            "length": 1017.988857051166,
            "slots": 320,
            "src": 23
        },
        {
            "dst": 24,
            "id": 80,
            "length": 1500.0,
            "slots": 320,
            "src": 21
        },
        {
            "dst": 21,
            "id": 81,
            "length": 1500.0,
            "slots": 320,
            "src": 24
        },
        {
            "dst": 24,
            "id": 82,
            "length": 1436.651367091551,
            "slots": 320,
            "src": 23
        },
        {
            "dst": 23,
            "id": 83,
            "length": 1436.651367091551,
            "slots": 320,
            "src": 24
        }
    ],
    "name": "TOP_54_JANOSUS",
    "nodes": [
        {
            "id": 0
        },
        {
            "id": 1
        },
        {
            "id": 2
        },
        {
            "id": 3
        },
        {
            "id": 4
        },
        {
            "id": 5
        },
        {
            "id": 6
        },
        {
            "id": 7
        },
        {
            "id": 8
        },
        {
            "id": 9
        },
        {
            "id": 10
        },
        {
            "id": 11
        },
        {
            "id": 12
        },
        {
            "id": 13
        },
        {
            "id": 14
        },
        {
            "id": 15
        },
        {
            "id": 16
        },
        {
            "id": 17
        },
        {
            "id": 18
        },
        {
            "id": 19
        },
        {
            "id": 20
        },
        {
            "id": 21
        },
        {
            "id": 22
        },
        {
            "id": 23
        },
        {
            "id": 24
        },
        {
            "id": 25
        }
    ]
}