{
    "alias": "ARPANET",
    "links": [
        {
            "dst": 1,
            "id": 0,
            "length": 1291.52838129584,
            "slots": 320,
            "src": 0
        },
        {
            "dst": 0,
            "id": 1,
            "length": 1291.52838129584,
            "slots": 320,
            "src": 1
        },
        {
            "dst": 3,
            "id": 2,
            "length": 1500.0,
            "slots": 320,
            "src": 0
        },
        {
            "dst": 0,
            "id": 3,
            "length": 1500.0,
            "slots": 320,
            "src": 3
        },
        {
            "dst": 6,
            "id": 4,
            "length": 2862.65129924126,
            "slots": 320,
            "src": 0
        },
        {
            "dst": 0,
            "id": 5,
            "length": 2862.65129924126,
            "slots": 320,
            "src": 6
        },
        {
            "dst": 3,
            "id": 6,
            "length": 1446.88092811279,
            "slots": 320,
            "src": 1
        },
        {
            "dst": 1,
            "id": 7,
            "length": 1446.88092811279,
            "slots": 320,
            "src": 3
        },
        {
            "dst": 2,
            "id": 8,
            "length": 839.100175042737,
            "slots": 320,
            "src": 1
        },
        {
            "dst": 1,
            "id": 9,
            "length": 839.100175042737,
            "slots": 320,
            "src": 2
        },
        {
            "dst": 5,
            "id": 10,
            "length": 894.712037640818,
            "slots": 320,
            "src": 3
        },
        {
            "dst": 3,
            "id": 11,
            "length": 894.712037640818,
            "slots": 320,
            "src": 5
        },
        {
            "dst": 5,
            "id": 12,
            "length": 1669.72936135601,
            "slots": 320,
            "src": 2
        },
        {
            "dst": 2,
            "id": 13,
            "length": 1669.72936135601,
            "slots": 320,
            "src": 5
        },
        {
            "dst": 4,
            "id": 14,
            "length": 268.87960244544,
            "slots": 320,
            "src": 2
        },
        {
            "dst": 2,
            "id": 15,
            "length": 268.87960244544,
            "slots": 320,
            "src": 4
        },
        {
            "dst": 7,
            "id": 16,
            "length": 1215.85558674533,
            "slots": 320,
            "src": 5
        },
        {
            "dst": 5,
            "id": 17,
            "length": 1215.85558674533,
            "slots": 320,
            "src": 7
        },
        {
            "dst": 7,
            "id": 18,
            "length": 2289.49496308338,
            "slots": 320,
            "src": 4
        },
        {
            "dst": 4,
            "id": 19,
            "length": 2289.49496308338,
            "slots": 320,
            "src": 7
        },
        {
            "dst": 8,
            "id": 20,
            "length": 2617.82611363942,
            "slots": 320,
            "src": 4
        },
        {
            "dst": 4,
            "id": 21,
            "length": 2617.82611363942,
            "slots": 320,
            "src": 8
        },
        {
            "dst": 11,
            "id": 22,
            "length": 1456.74238923334,
            "slots": 320,
            "src": 7
        },
        {
            "dst": 7,
            "id": 23,
            "length": 1456.74238923334,
            "slots": 320,
            "src": 11
        },
        {
            "dst": 11,
            "id": 24,
            "length": 1500.0,
            "slots": 320,
            "src": 8
        },
        {
            "dst": 8,
            "id": 25,
            "length": 1500.0,
            "slots": 320,
            "src": 11
        },
        {
            "dst": 9,
            "id": 26,
            "length": 1540.01331009159,
            "slots": 320,
            "src": 8
        },
        {
            "dst": 8,
            "id": 27,
            "length": 1540.01331009159,
            "slots": 320,
            "src": 9
        },
        {
            "dst": 10,
            "id": 28,
            "length": 765.854530392122,
            "slots": 320,
            "src": 8
        },
        {
            "dst": 8,
            "id": 29,
            "length": 765.854530392122,
            "slots": 320,
            "src": 10
        },
        {
            "dst": 12,
            "id": 30,
            "length": 1022.06273938179,
            "slots": 320,
            "src": 10
        },
        {
            "dst": 10,
            "id": 31,
            "length": 1022.06273938179,
            "slots": 320,
            "src": 12
        },
        {
            "dst": 13,
            "id": 32,
            "length": 1215.88923602322,
            "slots": 320,
            "src": 10
        },
        {
            "dst": 10,
            "id": 33,
            "length": 1215.88923602322,
            "slots": 320,
            "src": 13
        },
        {
            "dst": 12,
            "id": 34,
            "length": 688.597340870633,
            "slots": 320,
            "src": 13
        },
        {
            "dst": 13,
            "id": 35,
            "length": 688.597340870633,
            "slots": 320,
            "src": 12
        },
        {
            "dst": 14,
            "id": 36,
            "length": 618.093234639063,
            "slots": 320,
            "src": 13
        },
        {
            "dst": 13,
            "id": 37,
            "length": 618.093234639063,
            "slots": 320,
            "src": 14
        },
        {
            "dst": 15,
            "id": 38,
            "length": 976.493021315393,
            "slots": 320,
            "src": 14
        },
        {
            "dst": 14,
            "id": 39,
            "length": 976.493021315393,
            "slots": 320,
            "src": 15
        },
        {
            "dst": 19,
            "id": 40,
            "length": 1179.79022734108,
            "slots": 320,
            "src": 14
        },
        {
            "dst": 14,
            "id": 41,
            "length": 1179.79022734108,
            "slots": 320,
            "src": 19
        },
        {
            "dst": 19,
            "id": 42,
            "length": 1031.33977650974,
            "slots": 320,
            "src": 12
        },
        {
            "dst": 12,
            "id": 43,
            "length": 1031.33977650974,
            "slots": 320,
            "src": 19
        },
        {
            "dst": 18,
            "id": 44,
            "length": 1500.58239078238,
            "slots": 320,
            "src": 12
        },
        {
            "dst": 12,
            "id": 45,
            "length": 1500.58239078238,
            "slots": 320,
            "src": 18
        },
        {
            "dst": 15,
            "id": 46,
            "length": 1365.46574312549,
            "slots": 320,
            "src": 11
        },
        {
            "dst": 11,
            "id": 47,
            "length": 1365.46574312549,
            "slots": 320,
            "src": 15
        },
        {
            "dst": 9,
            "id": 48,
            "length": 714.232708493518,
            "slots": 320,
            "src": 11
        },
        {
            "dst": 11,
            "id": 49,
            "length": 714.232708493518,
            "slots": 320,
            "src": 9
        },
        {
            "dst": 6,
            "id": 50,
            "length": 971.861293046117,
            "slots": 320,
            "src": 9
        },
        {
            "dst": 9,
            "id": 51,
            "length": 971.861293046117,
            "slots": 320,
            "src": 6
        },
        {
            "dst": 17,
            "id": 52,
            "length": 579.54836901716,
            "slots": 320,
            "src": 19
        },
        {
            "dst": 19,
            "id": 53,
            "length": 579.54836901716,
            "slots": 320,
            "src": 17
        },
        {
            "dst": 6,
            "id": 54,
            "length": 1308.64012980237,
            "slots": 320,
            "src": 17
        },
        {
            "dst": 17,
            "id": 55,
            "length": 1308.64012980237,
            "slots": 320,
            "src": 6
        },
        {
            "dst": 16,
            "id": 56,
            "length": 495.582279184814,
            "slots": 320,
            "src": 17
        },
        {
            "dst": 17,
            "id": 57,
            "length": 495.582279184814,
            "slots": 320,
            "src": 16
        },
        {
            "dst": 18,
            "id": 58,
            "length": 759.284938573581,
            "slots": 320,
            "src": 16
        },
        {
            "dst": 16,
            "id": 59,
            "length": 759.284938573581,
            "slots": 320,
            "src": 18
        },
        {
            "dst": 15,
            "id": 60,
            "length": 458.588908811528,
            "slots": 320,
            "src": 16
        },
        {
            "dst": 16,
            "id": 61,
            "length": 458.588908811528,
            "slots": 320,
            "src": 15
        },
        {
            "dst": 15,
            "id": 62,
            "length": 492.602486220218,
            "slots": 320,
            "src": 18
        },
        {
            "dst": 18,
            "id": 63,
            "length": 492.602486220218,
            "slots": 320,
            "src": 15
        }
    ],
    "name": "TOP_4_ARPANET",
    "nodes": [
        {
            "id": 0
        },
        {
            "id": 1
        },
        {
            "id": 2
        },
        {
            "id": 3
        },
        {
            "id": 4
        },
        {
            "id": 5
        },
        {
            "id": 6
        },
        {
            "id": 7
        },
        {
            "id": 8
        },
        {
            "id": 9
        },
        {
            "id": 10
        },
        {
            "id": 11
        },
        {
            "id": 12
        },
        {
            "id": 13
        },
        {
            "id": 14
        },
        {
            "id": 15
        },
        {
            "id": 16
        },
        {
            "id": 17
        },
        {
            "id": 18
        },
        {
            "id": 19
        }
    ]
}